gym_mazeexplorer-0.0.10.dist-info/RECORD
gym_mazeexplorer-0.0.10.dist-info/top_level.txt
gym_mazeexplorer-0.0.10.dist-info/METADATA
gym_mazeexplorer-0.0.10.dist-info/metadata.json
gym_mazeexplorer-0.0.10.dist-info/DESCRIPTION.rst
gym_mazeexplorer-0.0.10.dist-info/WHEEL
gym_mazeexplorer/__init__.py
gym_mazeexplorer/test/__init__.py
gym_mazeexplorer/test/test_mazeexplorerenv.py
gym_mazeexplorer/envs/__init__.py
gym_mazeexplorer/envs/mazeexplorer_env.py
